{
  "project_info": {
    "project_number": "136374855501",
    "project_id": "habitool",
    "storage_bucket": "habitool.appspot.com"
  },
  "client": [
    {
      "client_info": {
        "mobilesdk_app_id": "1:136374855501:android:05a34520eb108b33f7b904",
        "android_client_info": {
          "package_name": "com.example.habitool"
        }
      },
      "oauth_client": [
        {
          "client_id": "136374855501-j7bjki443gq0gfc512mgctvb682bcc4k.apps.googleusercontent.com",
          "client_type": 1,
          "android_info": {
            "package_name": "com.example.habitool",
            "certificate_hash": "1ce708cf0d1092e090e096f1bbd164ad085d2d0a"
          }
        },
        {
          "client_id": "136374855501-frv20q5kck6vfpbajq4tjnm9gjagk73q.apps.googleusercontent.com",
          "client_type": 3
        }
      ],
      "api_key": [
        {
          "current_key": "AIzaSyDEOnTvDI3Xe-B9meGynyvAzuUisJzMnVw"
        }
      ],
      "services": {
        "appinvite_service": {
          "other_platform_oauth_client": [
            {
              "client_id": "136374855501-frv20q5kck6vfpbajq4tjnm9gjagk73q.apps.googleusercontent.com",
              "client_type": 3
            },
            {
              "client_id": "136374855501-fveu2boipp3ii56g24rc2ud3sn34lbs2.apps.googleusercontent.com",
              "client_type": 2,
              "ios_info": {
                "bundle_id": "com.example.habitool"
              }
            }
          ]
        }
      }
    }
  ],
  "configuration_version": "1"
}